threp/__init__.py
threp/api.py
threp/common.py
threp/decode.py
threp/static.py
threp/type.py
threp/utils.py
threp-2.1.1.dist-info/LICENSE
threp-2.1.1.dist-info/METADATA
threp-2.1.1.dist-info/WHEEL
threp-2.1.1.dist-info/top_level.txt
threp-2.1.1.dist-info/RECORD
