Metadata-Version: 2.1
Name: threp
Version: 2.1.1
Summary: decode Touhou Shooting Game's replay files and get the infomation in it
Home-page: https://github.com/wasupandceacar/threp
Author: wasupandceacar
Author-email: wasupandceacar@gmail.com
License: MIT
Keywords: touhou replay python
Platform: UNKNOWN
Classifier: Development Status :: 3 - Alpha
Classifier: Intended Audience :: Developers
Classifier: Topic :: Games/Entertainment
Classifier: Operating System :: OS Independent
Classifier: License :: OSI Approved :: MIT License
Classifier: Programming Language :: Python :: 3.6
Classifier: Programming Language :: Python :: 3.7
Classifier: Programming Language :: Python :: 3.8
Classifier: Programming Language :: Python :: 3.9
License-File: LICENSE
